Kala_Quantum/KalaQuantum.py
Kala_Quantum/__init__.py
Kala_Quantum-1.2.2.dist-info/METADATA
Kala_Quantum-1.2.2.dist-info/WHEEL
Kala_Quantum-1.2.2.dist-info/entry_points.txt
Kala_Quantum-1.2.2.dist-info/top_level.txt
Kala_Quantum-1.2.2.dist-info/RECORD
