Metadata-Version: 2.1
Name: Kala-Quantum
Version: 1.2.2
Summary: A quantum-powered chatbot framework leveraging quantum state manipulation for advanced conversational capabilities.
Home-page: https://github.com/Kalasaikamesh944/Kala_Quantum.git
Author: Your Name
Author-email: your.email@example.com
Classifier: Programming Language :: Python :: 3
Classifier: License :: OSI Approved :: MIT License
Classifier: Operating System :: OS Independent
Requires-Python: >=3.6
Requires-Dist: numpy
Requires-Dist: termcolor
Requires-Dist: torch
Requires-Dist: tqdm
